Workbook

Sheet 使用说明
A1: 高新技术企业预评估双年度采集表
A2: 用于比较今年申报与明年申报；黄色为输入，绿色为公式结果。内部 75 分缓冲线不是官方政策门槛。
A4: 步骤 | B4: 工作表 | C4: 填写内容 | D4: 填写责任人 | E4: 结果 | F4: 是否必须 | G4: 注意事项 | H4: 完成状态
A5: 1 | B5: 基础与硬门槛 | C5: 企业、地区、申报类型及九项硬门槛 | D5: 项目负责人/财务/人事 | E5: 当年及明年硬门槛状态 | F5: 是 | G5: 成长性 0 分不是硬门槛不通过 | H5: 未开始
A6: 2 | B6: 财务与成长性 | C6: 四年度收入、净资产、研发、高品收入和人员 | D6: 财务 | E6: 两年度成长性及硬比例 | F6: 是 | G6: 预测数据必须标明预测 | H6: 未开始
A7: 3 | B7: 知识产权 | C7: 逐件录入法律状态、权属、使用历史和关联 | D7: 知识产权/技术 | E7: 本次可用性 | F7: 是 | G7: 曾申报未通过不消耗Ⅱ类使用次数 | H7: 未开始
A8: 4 | B8: 成果转化 | C8: 逐项录入成果来源、过程、载体和应用成效 | D8: 技术/生产/销售 | E8: 三年保守有效数量 | F8: 是 | G8: 同一成果不得重复拆分 | H8: 未开始
A9: 5 | B9: 组织管理 | C9: 制度、执行、结果及三档评分 | D9: 研发/人事/财务 | E9: 目标/保守/压力分 | F9: 是 | G9: 制度文件不等于制度执行 | H9: 未开始
A10: 6 | B10: 双年度评分 | C10: 录入知识产权三档分，复核自动建议 | D10: 项目负责人 | E10: 申报年度建议 | F10: 是 | G10: 先看保守分，再看压力分 | H10: 未开始
A11: 7 | B11: 补强计划 | C11: 把缺口转成动作、证据和截止时间 | D11: 项目负责人 | E11: 可执行整改表 | F11: 是 | G11: 区分证据补强和事实补强 | H11: 未开始
A12: 8 | B12: 规则与来源 | C12: 核验当期政策与属地通知 | D12: 项目负责人 | E12: 来源可追溯 | F12: 是 | G12: 地方经验不得冒充国家政策 | H12: 未开始
A13: 9 | B13: 最终复核 | C13: 跨表核对专利、研发、成果、高品和收入 | D13: 复核人 | E13: 最终结论 | F13: 是 | G13: 任何矛盾保留并说明 | H13: 未开始
A15: 输出等级
A16: 等级 | B16: 判定 | C16: 硬门槛 | D16: 保守分 | E16: 压力分 | F16: 年度比较 | G16: 建议 | H16: 说明
A17: A | B17: 建议当年申报 | C17: 全部通过 | D17: ≥75 | E17: 原则上≥71 | F17: 下一年净改善有限 | G17: 今年申报 | H17: 仍需以当期政策和正式材料为准
A18: B | B18: 补强后当年申报 | C18: 全部通过 | D18: 71—74 | E18: 存在可控争议 | F18: 截止前可真实补强 | G18: 补强后今年申报 | H18: 补强后重新评分
A19: C | B19: 建议下一年申报 | C19: 当年通过或可整改 | D19: ≤70 | E19: 明显偏低 | F19: 下一年有可验证净改善 | G19: 明年申报 | H19: 必须扣除退出年度损失
A20: D | B20: 两年均暂缓 | C20: 存在持续否决项 | D20: 不足 | E20: 不足 | F20: 下一年改善不确定 | G20: 暂缓 | H20: 先解决硬门槛或真实性问题

Sheet 基础与硬门槛
A1: 基础信息与硬门槛
A2: “否”触发不通过；“待核”触发待核。成长性得分不在本表作为硬门槛。
A4: 基础字段 | B4: 填写值
A5: 企业名称
A6: 统一社会信用代码
A7: 申报地区 | B7: 浙江省
A8: 拟申报年度 | B8: 2026
A9: 申报类型 | B9: 首次认定
A10: 当前填表日期 | B10: 46227
A12: 硬门槛逐项核验
A13: 序号 | B13: 硬门槛 | C13: 当年状态 | D13: 下一年预测 | E13: 事实/资料来源 | F13: 缺口及处理
A14: 1 | B14: 注册成立一年以上 | C14: 待核 | D14: 待核
A15: 2 | B15: 拥有核心知识产权所有权 | C15: 待核 | D15: 待核
A16: 3 | B16: 核心技术属于高新技术领域 | C16: 待核 | D16: 待核
A17: 4 | B17: 科技人员占比不低于10% | C17: 待核 | D17: 待核
A18: 5 | B18: 研发费用占比达到对应档次 | C18: 待核 | D18: 待核
A19: 6 | B19: 境内研发费用占比不低于60% | C19: 待核 | D19: 待核
A20: 7 | B20: 高新产品或服务收入占比不低于60% | C20: 待核 | D20: 待核
A21: 8 | B21: 创新能力评价超过70分 | C21: 待核 | D21: 待核
A22: 9 | B22: 前一年无重大事故或严重环境违法 | C22: 待核 | D22: 待核
A24: 汇总结论 | B24: 当年
A25: 当年硬门槛 | B25: =IF(COUNTIF(C14:C22,"否")>0,"不通过",IF(OR(COUNTIF(C14:C22,"待核")>0,COUNTBLANK(C14:C22)>0),"待核","通过"))
A26: 下一年硬门槛 | B26: =IF(COUNTIF(D14:D22,"否")>0,"不通过",IF(OR(COUNTIF(D14:D22,"待核")>0,COUNTBLANK(D14:D22)>0),"待核","通过"))

Sheet 财务与成长性
A1: 财务、人员与成长性
A2: 录入连续四个年度。前三列用于当年申报，后三列用于下一年申报；预测值必须在口径列说明。
A4: 项目 | B4: Y-3 | C4: Y-2 | D4: Y-1 | E4: Y | F4: 单位 | G4: 数据口径 | H4: 备注
A5: 年度 | B5: 2023 | C5: 2024 | D5: 2025 | E5: 2026 | F5: 年 | G5: 实际/预测
A6: 销售收入 | F6: 万元
A7: 净资产 | F7: 万元
A8: 研发费用 | F8: 万元
A9: 境内研发费用 | F9: 万元
A10: 总收入 | F10: 万元
A11: 高新产品或服务收入 | F11: 万元
A12: 职工总数 | F12: 人
A13: 科技人员数 | F13: 人
A14: 最近一年销售收入档次 | D14: =IF(D6<=5000,"≤5000万元，研发费比例≥5%",IF(D6<=20000,"5000万—2亿元，研发费比例≥4%",">2亿元，研发费比例≥3%")) | E14: =IF(E6<=5000,"≤5000万元，研发费比例≥5%",IF(E6<=20000,"5000万—2亿元，研发费比例≥4%",">2亿元，研发费比例≥3%"))
A16: 硬比例自动计算
A17: 指标 | B17: 当年使用值 | C17: 当年门槛 | D17: 当年判断 | E17: 下一年使用值 | F17: 下一年门槛 | G17: 下一年判断 | H17: 说明
A18: 近三年研发费用占销售收入比例 | B18: =IF(OR(COUNT(B8:D8,B6:D6)<6,SUM(B6:D6)=0),"待核",SUM(B8:D8)/SUM(B6:D6)) | C18: =IF(D6<=5000,5%,IF(D6<=20000,4%,3%)) | D18: =IF(ISNUMBER(B18),IF(B18>=C18,"是","否"),"待核") | E18: =IF(OR(COUNT(C8:E8,C6:E6)<6,SUM(C6:E6)=0),"待核",SUM(C8:E8)/SUM(C6:E6)) | F18: =IF(E6<=5000,5%,IF(E6<=20000,4%,3%)) | G18: =IF(ISNUMBER(E18),IF(E18>=F18,"是","否"),"待核") | H18: 按三年合计计算
A19: 境内研发费用占研发费用比例 | B19: =IF(OR(COUNT(B9:D9,B8:D8)<6,SUM(B8:D8)=0),"待核",SUM(B9:D9)/SUM(B8:D8)) | C19: 0.6 | D19: =IF(ISNUMBER(B19),IF(B19>=C19,"是","否"),"待核") | E19: =IF(OR(COUNT(C9:E9,C8:E8)<6,SUM(C8:E8)=0),"待核",SUM(C9:E9)/SUM(C8:E8)) | F19: 0.6 | G19: =IF(ISNUMBER(E19),IF(E19>=F19,"是","否"),"待核") | H19: 不低于60%
A20: 最近一年高品收入占总收入比例 | B20: =IF(OR(COUNT(D11,D10)<2,SUM(D10)=0),"待核",SUM(D11)/SUM(D10)) | C20: 0.6 | D20: =IF(ISNUMBER(B20),IF(B20>=C20,"是","否"),"待核") | E20: =IF(OR(COUNT(E11,E10)<2,SUM(E10)=0),"待核",SUM(E11)/SUM(E10)) | F20: 0.6 | G20: =IF(ISNUMBER(E20),IF(E20>=F20,"是","否"),"待核") | H20: 不低于60%
A21: 最近一年科技人员占比 | B21: =IF(OR(COUNT(D13,D12)<2,SUM(D12)=0),"待核",SUM(D13)/SUM(D12)) | C21: 0.1 | D21: =IF(ISNUMBER(B21),IF(B21>=C21,"是","否"),"待核") | E21: =IF(OR(COUNT(E13,E12)<2,SUM(E12)=0),"待核",SUM(E13)/SUM(E12)) | F21: 0.1 | G21: =IF(ISNUMBER(E21),IF(E21>=F21,"是","否"),"待核") | H21: 不低于10%；人员数据缺失或分母为零时为待核，不能按零或不达标处理。
A23: 成长性自动计算
A24: 指标 | B24: 当年增长率 | C24: 当年复核 | D24: 当年保守分 | E24: 下一年增长率 | F24: 下一年复核 | G24: 下一年保守分 | H24: 官方分数区间
A25: 销售收入增长率 | B25: =IF(OR(B6<0,C6<0),0,IF(C6=0,0,IF(B6=0,D6/C6-1,0.5*(C6/B6+D6/C6)-1))) | C25: =IF(OR(B6<0,C6<0),"专项复核",IF(C6=0,"第二年为0",IF(B6=0,"按后两年计算","正常"))) | D25: =IF(B25<=0,0,IF(B25>=35%,9,IF(B25>=25%,7,IF(B25>=15%,5,IF(B25>=5%,3,1))))) | E25: =IF(OR(C6<0,D6<0),0,IF(D6=0,0,IF(C6=0,E6/D6-1,0.5*(D6/C6+E6/D6)-1))) | F25: =IF(OR(C6<0,D6<0),"专项复核",IF(D6=0,"第二年为0",IF(C6=0,"按后两年计算","正常"))) | G25: =IF(E25<=0,0,IF(E25>=35%,9,IF(E25>=25%,7,IF(E25>=15%,5,IF(E25>=5%,3,1))))) | H25: 每项最高10分
A26: 净资产增长率 | B26: =IF(OR(B7<0,C7<0),0,IF(C7=0,0,IF(B7=0,D7/C7-1,0.5*(C7/B7+D7/C7)-1))) | C26: =IF(OR(B7<0,C7<0),"专项复核",IF(C7=0,"第二年为0",IF(B7=0,"按后两年计算","正常"))) | D26: =IF(B26<=0,0,IF(B26>=35%,9,IF(B26>=25%,7,IF(B26>=15%,5,IF(B26>=5%,3,1))))) | E26: =IF(OR(C7<0,D7<0),0,IF(D7=0,0,IF(C7=0,E7/D7-1,0.5*(D7/C7+E7/D7)-1))) | F26: =IF(OR(C7<0,D7<0),"专项复核",IF(D7=0,"第二年为0",IF(C7=0,"按后两年计算","正常"))) | G26: =IF(E26<=0,0,IF(E26>=35%,9,IF(E26>=25%,7,IF(E26>=15%,5,IF(E26>=5%,3,1))))) | H26: 每项最高10分

Sheet 知识产权
A1: 知识产权逐件采集
A2: 关键规则：曾申报未通过不消耗Ⅱ类使用次数；Ⅱ类只有曾在通过认定中使用，才判为本次不可重复使用。
A4: IP编号 | B4: 类别 | C4: 类型 | D4: 名称 | E4: 申请号 | F4: 授权号 | G4: 授权日 | H4: 法律状态 | I4: 权属符合 | J4: 获得方式 | K4: 曾申报未通过使用 | L4: 曾在通过认定中使用 | M4: 对应RD | N4: 核心技术 | O4: 对应高品 | P4: 核心支持强度 | Q4: 证据完整度 | R4: 本次可用性 | S4: 备注
A5: IP01 | K5: 否 | L5: 否 | R5: =IF(D5="","",IF(H5<>"有效","不可用：未有效",IF(I5<>"是","不可用：权属",IF(AND(B5="Ⅱ类",L5="是"),"不可用：已用于通过认定","可用"))))
A6: IP02 | K6: 否 | L6: 否 | R6: =IF(D6="","",IF(H6<>"有效","不可用：未有效",IF(I6<>"是","不可用：权属",IF(AND(B6="Ⅱ类",L6="是"),"不可用：已用于通过认定","可用"))))
A7: IP03 | K7: 否 | L7: 否 | R7: =IF(D7="","",IF(H7<>"有效","不可用：未有效",IF(I7<>"是","不可用：权属",IF(AND(B7="Ⅱ类",L7="是"),"不可用：已用于通过认定","可用"))))
A8: IP04 | K8: 否 | L8: 否 | R8: =IF(D8="","",IF(H8<>"有效","不可用：未有效",IF(I8<>"是","不可用：权属",IF(AND(B8="Ⅱ类",L8="是"),"不可用：已用于通过认定","可用"))))
A9: IP05 | K9: 否 | L9: 否 | R9: =IF(D9="","",IF(H9<>"有效","不可用：未有效",IF(I9<>"是","不可用：权属",IF(AND(B9="Ⅱ类",L9="是"),"不可用：已用于通过认定","可用"))))
A10: IP06 | K10: 否 | L10: 否 | R10: =IF(D10="","",IF(H10<>"有效","不可用：未有效",IF(I10<>"是","不可用：权属",IF(AND(B10="Ⅱ类",L10="是"),"不可用：已用于通过认定","可用"))))
A11: IP07 | K11: 否 | L11: 否 | R11: =IF(D11="","",IF(H11<>"有效","不可用：未有效",IF(I11<>"是","不可用：权属",IF(AND(B11="Ⅱ类",L11="是"),"不可用：已用于通过认定","可用"))))
A12: IP08 | K12: 否 | L12: 否 | R12: =IF(D12="","",IF(H12<>"有效","不可用：未有效",IF(I12<>"是","不可用：权属",IF(AND(B12="Ⅱ类",L12="是"),"不可用：已用于通过认定","可用"))))
A13: IP09 | K13: 否 | L13: 否 | R13: =IF(D13="","",IF(H13<>"有效","不可用：未有效",IF(I13<>"是","不可用：权属",IF(AND(B13="Ⅱ类",L13="是"),"不可用：已用于通过认定","可用"))))
A14: IP10 | K14: 否 | L14: 否 | R14: =IF(D14="","",IF(H14<>"有效","不可用：未有效",IF(I14<>"是","不可用：权属",IF(AND(B14="Ⅱ类",L14="是"),"不可用：已用于通过认定","可用"))))
A15: IP11 | K15: 否 | L15: 否 | R15: =IF(D15="","",IF(H15<>"有效","不可用：未有效",IF(I15<>"是","不可用：权属",IF(AND(B15="Ⅱ类",L15="是"),"不可用：已用于通过认定","可用"))))
A16: IP12 | K16: 否 | L16: 否 | R16: =IF(D16="","",IF(H16<>"有效","不可用：未有效",IF(I16<>"是","不可用：权属",IF(AND(B16="Ⅱ类",L16="是"),"不可用：已用于通过认定","可用"))))
... A104: IP100 | K104: 否 | L104: 否 | R104: =IF(D104="","",IF(H104<>"有效","不可用：未有效",IF(I104<>"是","不可用：权属",IF(AND(B104="Ⅱ类",L104="是"),"不可用：已用于通过认定","可用"))))

Sheet 成果转化
A1: 科技成果转化逐项采集
A2: 保守计数要求成果来源、转化过程、转化载体和应用成效形成证据链；同一成果不得重复拆分。
A4: 转化编号 | B4: 年度 | C4: 成果名称 | D4: 成果来源类型 | E4: 来源编号 | F4: 技术边界 | G4: 转化过程证据 | H4: 转化载体 | I4: 应用成效证据 | J4: 对应高品 | K4: 对应收入 | L4: 独立成果 | M4: 是否重复 | N4: 保守判断 | O4: 保守计数 | P4: 争议与备注
A5: CT01 | L5: 待核 | M5: 待核 | N5: =IF(C5="","",IF(AND(F5<>"",G5<>"",H5<>"",I5<>"",L5="是",M5="否"),"计1项",IF(AND(H5<>"",I5<>"",L5="是",M5="否"),"中等证据","保守不计"))) | O5: =IF(OR(N5="计1项",N5="中等证据"),1,0)
A6: CT02 | L6: 待核 | M6: 待核 | N6: =IF(C6="","",IF(AND(F6<>"",G6<>"",H6<>"",I6<>"",L6="是",M6="否"),"计1项",IF(AND(H6<>"",I6<>"",L6="是",M6="否"),"中等证据","保守不计"))) | O6: =IF(OR(N6="计1项",N6="中等证据"),1,0)
A7: CT03 | L7: 待核 | M7: 待核 | N7: =IF(C7="","",IF(AND(F7<>"",G7<>"",H7<>"",I7<>"",L7="是",M7="否"),"计1项",IF(AND(H7<>"",I7<>"",L7="是",M7="否"),"中等证据","保守不计"))) | O7: =IF(OR(N7="计1项",N7="中等证据"),1,0)
A8: CT04 | L8: 待核 | M8: 待核 | N8: =IF(C8="","",IF(AND(F8<>"",G8<>"",H8<>"",I8<>"",L8="是",M8="否"),"计1项",IF(AND(H8<>"",I8<>"",L8="是",M8="否"),"中等证据","保守不计"))) | O8: =IF(OR(N8="计1项",N8="中等证据"),1,0)
A9: CT05 | L9: 待核 | M9: 待核 | N9: =IF(C9="","",IF(AND(F9<>"",G9<>"",H9<>"",I9<>"",L9="是",M9="否"),"计1项",IF(AND(H9<>"",I9<>"",L9="是",M9="否"),"中等证据","保守不计"))) | O9: =IF(OR(N9="计1项",N9="中等证据"),1,0)
A10: CT06 | L10: 待核 | M10: 待核 | N10: =IF(C10="","",IF(AND(F10<>"",G10<>"",H10<>"",I10<>"",L10="是",M10="否"),"计1项",IF(AND(H10<>"",I10<>"",L10="是",M10="否"),"中等证据","保守不计"))) | O10: =IF(OR(N10="计1项",N10="中等证据"),1,0)
A11: CT07 | L11: 待核 | M11: 待核 | N11: =IF(C11="","",IF(AND(F11<>"",G11<>"",H11<>"",I11<>"",L11="是",M11="否"),"计1项",IF(AND(H11<>"",I11<>"",L11="是",M11="否"),"中等证据","保守不计"))) | O11: =IF(OR(N11="计1项",N11="中等证据"),1,0)
A12: CT08 | L12: 待核 | M12: 待核 | N12: =IF(C12="","",IF(AND(F12<>"",G12<>"",H12<>"",I12<>"",L12="是",M12="否"),"计1项",IF(AND(H12<>"",I12<>"",L12="是",M12="否"),"中等证据","保守不计"))) | O12: =IF(OR(N12="计1项",N12="中等证据"),1,0)
A13: CT09 | L13: 待核 | M13: 待核 | N13: =IF(C13="","",IF(AND(F13<>"",G13<>"",H13<>"",I13<>"",L13="是",M13="否"),"计1项",IF(AND(H13<>"",I13<>"",L13="是",M13="否"),"中等证据","保守不计"))) | O13: =IF(OR(N13="计1项",N13="中等证据"),1,0)
A14: CT10 | L14: 待核 | M14: 待核 | N14: =IF(C14="","",IF(AND(F14<>"",G14<>"",H14<>"",I14<>"",L14="是",M14="否"),"计1项",IF(AND(H14<>"",I14<>"",L14="是",M14="否"),"中等证据","保守不计"))) | O14: =IF(OR(N14="计1项",N14="中等证据"),1,0)
A15: CT11 | L15: 待核 | M15: 待核 | N15: =IF(C15="","",IF(AND(F15<>"",G15<>"",H15<>"",I15<>"",L15="是",M15="否"),"计1项",IF(AND(H15<>"",I15<>"",L15="是",M15="否"),"中等证据","保守不计"))) | O15: =IF(OR(N15="计1项",N15="中等证据"),1,0)
A16: CT12 | L16: 待核 | M16: 待核 | N16: =IF(C16="","",IF(AND(F16<>"",G16<>"",H16<>"",I16<>"",L16="是",M16="否"),"计1项",IF(AND(H16<>"",I16<>"",L16="是",M16="否"),"中等证据","保守不计"))) | O16: =IF(OR(N16="计1项",N16="中等证据"),1,0)
... A104: CT100 | L104: 待核 | M104: 待核 | N104: =IF(C104="","",IF(AND(F104<>"",G104<>"",H104<>"",I104<>"",L104="是",M104="否"),"计1项",IF(AND(H104<>"",I104<>"",L104="是",M104="否"),"中等证据","保守不计"))) | O104: =IF(OR(N104="计1项",N104="中等证据"),1,0)

Sheet 组织管理
A1: 研发组织管理证据评分
A2: 内部拆分仅用于预评估。保守分必须由真实执行记录支撑，不能以制度文本代替执行。
A4: 维度 | B4: 核查事项 | C4: 参考上限 | D4: 事实状态 | E4: 直接证据/路径 | F4: 执行起始时间 | G4: 目标分 | H4: 保守分 | I4: 压力分 | J4: 缺口性质 | K4: 补强动作
A5: 研发管理与核算 | B5: 制度正式发布、职责清楚 | C5: 1 | D5: 待核
A6: 研发管理与核算 | B6: 真实立项、评审、过程和结题 | C6: 2 | D6: 待核
A7: 研发管理与核算 | B7: 研发核算体系和辅助账 | C7: 2 | D7: 待核
A8: 研发管理与核算 | B8: 项目、人员、费用、成果对应 | C8: 1 | D8: 待核
A9: 研发机构与条件 | B9: 内部研发机构及职责 | C9: 2 | D9: 待核
A10: 研发机构与条件 | B10: 人员、场地、设备和试验条件 | C10: 2 | D10: 待核
A11: 研发机构与条件 | B11: 产学研合作及实际技术交付 | C11: 2 | D11: 待核
A12: 成果转化与激励 | B12: 成果转化组织实施制度 | C12: 1 | D12: 待核
A13: 成果转化与激励 | B13: 激励奖励制度 | C13: 1 | D13: 待核
A14: 成果转化与激励 | B14: 实际奖励记录 | C14: 1 | D14: 待核
A15: 成果转化与激励 | B15: 开放创新平台或活动 | C15: 1 | D15: 待核
A16: 人才培养与绩效 | B16: 培养、培训和人才引进 | C16: 2 | D16: 待核
A17: 人才培养与绩效 | B17: 绩效评价及实际奖励 | C17: 2 | D17: 待核
A19: 汇总 | B19: 参考上限 | C19: 目标分 | D19: 保守分 | E19: 压力分 | F19: 校验
A20: 研发组织管理合计 | B20: =SUM(C5:C17) | C20: =SUM(G5:G17) | D20: =SUM(H5:H17) | E20: =SUM(I5:I17) | F20: =IF(AND(E20<=D20,D20<=C20,C20<=B20),"通过","检查压力≤保守≤目标及上限")
A21: 关系校验 | F21: =IF(COUNTIF(D5:D17,"待核")>0,"仍有待核项","状态已填写")
A22: 结论 | F22: =IF(F20<>"通过","不可用于评分",IF(D20>=18,"证据较强",IF(D20>=16,"存在压分风险","需实质补强")))

Sheet 双年度评分
A1: 双年度评分与申报建议
A2: 以保守分作为主要决策依据，以压力分识别专家争议；知识产权三档分需按证据规则人工评定。
A4: 指标 | B4: 当年目标分 | C4: 当年保守分 | D4: 当年压力分 | E4: 下一年目标分 | F4: 下一年保守分 | G4: 下一年压力分 | H4: 满分 | I4: 评分依据 | J4: 补强重点
A5: 知识产权 | H5: 30 | I5: 按先进性、核心支持、数量和获得方式评定
A6: 科技成果转化 | B6: =IF(B18>=5,30,IF(B18>=4,24,IF(B18>=3,18,IF(B18>=2,12,IF(B18>=1,6,0))))) | C6: =IF(B18>=5,25,IF(B18>=4,19,IF(B18>=3,13,IF(B18>=2,7,IF(B18>=1,1,0))))) | D6: =IF(C6=0,0,MAX(0,C6-2)) | E6: =IF(E18>=5,30,IF(E18>=4,24,IF(E18>=3,18,IF(E18>=2,12,IF(E18>=1,6,0))))) | F6: =IF(E18>=5,25,IF(E18>=4,19,IF(E18>=3,13,IF(E18>=2,7,IF(E18>=1,1,0))))) | G6: =IF(F6=0,0,MAX(0,F6-2)) | H6: 30 | I6: 按近三年年平均数及证据质量评定
A7: 研发组织管理 | B7: ='组织管理'!C20 | C7: ='组织管理'!D20 | D7: ='组织管理'!E20 | E7: ='组织管理'!C20 | F7: ='组织管理'!D20 | G7: ='组织管理'!E20 | H7: 20 | I7: 从组织管理表汇总
A8: 企业成长性 | B8: =IF('财务与成长性'!B25<=0,0,IF('财务与成长性'!B25>=35%,10,IF('财务与成长性'!B25>=25%,8,IF('财务与成长性'!B25>=15%,6,IF('财务与成长性'!B25>=5%,4,2)))))+IF('财务与成长性'!B26<=0,0,IF('财务与成长性'!B26>=35%,10,IF('财务与成长性'!B26>=25%,8,IF('财务与成长性'!B26>=15%,6,IF('财务与成长性'!B26>=5%,4,2))))) | C8: ='财务与成长性'!D25+'财务与成长性'!D26 | D8: =C8 | E8: =IF('财务与成长性'!E25<=0,0,IF('财务与成长性'!E25>=35%,10,IF('财务与成长性'!E25>=25%,8,IF('财务与成长性'!E25>=15%,6,IF('财务与成长性'!E25>=5%,4,2)))))+IF('财务与成长性'!E26<=0,0,IF('财务与成长性'!E26>=35%,10,IF('财务与成长性'!E26>=25%,8,IF('财务与成长性'!E26>=15%,6,IF('财务与成长性'!E26>=5%,4,2))))) | F8: ='财务与成长性'!G25+'财务与成长性'!G26 | G8: =F8 | H8: 20 | I8: 从财务表自动计算
A10: 汇总 | B10: 当年目标 | C10: 当年保守 | D10: 当年压力 | E10: 下一年目标 | F10: 下一年保守 | G10: 下一年压力 | H10: 满分
A11: 总分 | B11: =SUM(B5:B8) | C11: =SUM(C5:C8) | D11: =SUM(D5:D8) | E11: =SUM(E5:E8) | F11: =SUM(F5:F8) | G11: =SUM(G5:G8) | H11: 100
A12: 硬门槛 | B12: ='基础与硬门槛'!B25 | E12: ='基础与硬门槛'!B26
A13: 建议 | B13: =IF(B12<>"通过","当年硬门槛未通过或待核，先整改",IF(C11>=75,IF(D11>=71,"建议今年申报","今年可报但专家争议较大"),IF(C11>=71,"补强后今年申报",IF(AND(E12="通过",F11>=75),"建议明年申报","两年均暂缓或继续补强"))))
A15: 滚动窗口计算
A16: 项目 | B16: 当年 | C16: 说明 | E16: 下一年 | F16: 说明
A17: 保守有效成果数 | B17: =SUMIFS('成果转化'!$O$5:$O$104,'成果转化'!$B$5:$B$104,">="&'财务与成长性'!B5,'成果转化'!$B$5:$B$104,"<="&'财务与成长性'!D5) | C17: 按三年度计数 | E17: =SUMIFS('成果转化'!$O$5:$O$104,'成果转化'!$B$5:$B$104,">="&'财务与成长性'!C5,'成果转化'!$B$5:$B$104,"<="&'财务与成长性'!E5) | F17: 按三年度计数
A18: 年平均转化数 | B18: =B17/3 | C18: 用于成果转化评分档 | E18: =E17/3 | F18: 用于成果转化评分档

Sheet 补强计划
A1: 补强计划
A2: 证据补强用于整理已发生事实；事实补强必须真实执行并持续留痕，不得倒签或补造。
A4: 优先级 | B4: 缺口 | C4: 当前影响 | D4: 补强性质 | E4: 具体动作 | F4: 证据产物 | G4: 预计增分 | H4: 截止时间 | I4: 责任岗位 | J4: 完成状态 | K4: 复核结果
A5: 中 | D5: 待核 | J5: 未开始
A6: 中 | D6: 待核 | J6: 未开始
A7: 中 | D7: 待核 | J7: 未开始
A8: 中 | D8: 待核 | J8: 未开始
A9: 中 | D9: 待核 | J9: 未开始
A10: 中 | D10: 待核 | J10: 未开始
A11: 中 | D11: 待核 | J11: 未开始
A12: 中 | D12: 待核 | J12: 未开始
A13: 中 | D13: 待核 | J13: 未开始
A14: 中 | D14: 待核 | J14: 未开始
A15: 中 | D15: 待核 | J15: 未开始
A16: 中 | D16: 待核 | J16: 未开始
... A64: 中 | D64: 待核 | J64: 未开始

Sheet 规则与来源
A1: 规则、口径与来源
A2: 每次正式评估仍需核验当期国家规则、属地通知和系统要求。
A4: 类别 | B4: 规则 | C4: 当前口径 | D4: 来源层级 | E4: 来源或确认人 | F4: 核验日期
A5: 政策 | B5: 创新能力评价 | C5: 总分100，综合得分超过70 | D5: 国家文件 | E5: https://www.most.gov.cn/xxgk/xinxifenlei/fdzdgknr/fgzc/gfxwj/gfxwj2016/201602/t20160205_123998.html | F5: 46227
A6: 政策 | B6: 工作指引 | C6: 知识产权、成果转化、组织管理和成长性评分 | D6: 国家文件 | E6: http://heilongjiang.chinatax.gov.cn/art/2016/6/22/art_4912_153619.html | F6: 46227
A7: 内部风控 | B7: 保守缓冲线 | C7: 75分为内部建议线，不是政策门槛 | D7: 内部规则 | E7: high-tech-enterprise-preassessment | F7: 46227
A8: 实务口径 | B8: Ⅱ类曾申报未通过 | C8: 未通过不消耗使用次数，可在后续申报再次使用 | D8: 主人确认 | E8: 用户于当前任务明确确认 | F8: 46227
A9: 实务口径 | B9: Ⅱ类曾在通过认定中使用 | C9: 本次不可重复使用 | D9: 工作基线 | E9: 结合工作指引与主人确认口径 | F9: 46227
A10: 证据规则 | B10: 未授权知识产权 | C10: 申请中不计入有效知识产权得分 | D10: 工作指引 | E10: 国家文件及属地核验 | F10: 46227
A11: 证据规则 | B11: 成果转化重复 | C11: 同一成果多产品或多地区不重复计数 | D11: 工作指引 | E11: 国家文件 | F11: 46227
A12: 证据规则 | B12: 组织管理 | C12: 制度、执行、结果三层核验 | D12: 内部预评估 | E12: 技能评分规则 | F12: 46227
A13: 真实性 | B13: 补强边界 | C13: 区分证据补强与事实补强，禁止倒签补造 | D13: 质量门禁 | E13: 焦糖工作约定 | F13: 46227
A14: 输出 | B14: 通过率 | C14: 无校准样本时只给把握等级和安全边际 | D14: 真实性规则 | E14: 技能主流程 | F14: 46227
